pythemis/__init__.py
pythemis/exception.py
pythemis/scell.py
pythemis/scomparator.py
pythemis/skeygen.py
pythemis/smessage.py
pythemis/ssession.py
pythemis-0.15.0.dist-info/AUTHORS
pythemis-0.15.0.dist-info/LICENSE
pythemis-0.15.0.dist-info/METADATA
pythemis-0.15.0.dist-info/WHEEL
pythemis-0.15.0.dist-info/top_level.txt
pythemis-0.15.0.dist-info/RECORD
